MANIFEST.in
README.md
requirements.txt
setup.py
dorthy/__init__.py
dorthy/background.py
dorthy/cache.py
dorthy/db.py
dorthy/dp.py
dorthy/email.py
dorthy/enum.py
dorthy/json.py
dorthy/logging.py
dorthy/redis.py
dorthy/request.py
dorthy/sentry.py
dorthy/settings.py
dorthy/template.py
dorthy/upload.py
dorthy/utils.py
dorthy/web.py
dorthy.egg-info/PKG-INFO
dorthy.egg-info/SOURCES.txt
dorthy.egg-info/dependency_links.txt
dorthy.egg-info/not-zip-safe
dorthy.egg-info/requires.txt
dorthy.egg-info/top_level.txt
dorthy/security/__init__.py
dorthy/security/access.py
dorthy/security/auth.py
dorthy/security/auth_handler.py
dorthy/security/auth_signed.py
dorthy/security/core.py
dorthy/security/crypto.py
dorthy/session/__init__.py
dorthy/session/base.py
dorthy/session/db.py
dorthy/session/redis.py