Metadata-Version: 1.1
Name: dorthy
Version: 0.7.6
Summary: a micro web framework for Tornado
Home-page: https://github.com/MobileDynasty/dorthy
Author: dev@mobile-dynasty.com
Author-email: dev@mobile-dynasty.com
License: MIT
Keywords: web framework development
Platform: UNKNOWN
Classifier: Development Status :: 4 - Beta
Classifier: Intended Audience :: Developers
Classifier: Topic :: Internet :: WWW/HTTP
Classifier: License :: OSI Approved :: MIT License
Classifier: Programming Language :: Python :: 3.2
Classifier: Programming Language :: Python :: 3.3
Classifier: Programming Language :: Python :: 3.4
